backutil/__init__.py
backutil-0.1.6.data/scripts/backutil
backutil-0.1.6.dist-info/LICENSE
backutil-0.1.6.dist-info/METADATA
backutil-0.1.6.dist-info/WHEEL
backutil-0.1.6.dist-info/top_level.txt
backutil-0.1.6.dist-info/RECORD
