Metadata-Version: 2.1
Name: backutil
Version: 0.1.6
Summary: Python backup utility
Home-page: https://github.com/heywoodlh/backutil
Author: Spencer Heywood
Author-email: l.spencer.heywood@gmail.com
License: APACHE-2.0
Platform: UNKNOWN
Requires-Dist: requests
Requires-Dist: python-gnupg
